livekit/plugins/uplift/__init__.py
livekit/plugins/uplift/log.py
livekit/plugins/uplift/models.py
livekit/plugins/uplift/tts.py
livekit/plugins/uplift/version.py
livekit_plugins_uplift-0.2.9.dist-info/METADATA
livekit_plugins_uplift-0.2.9.dist-info/WHEEL
livekit_plugins_uplift-0.2.9.dist-info/licenses/LICENSE
livekit_plugins_uplift-0.2.9.dist-info/RECORD
