Metadata-Version: 2.4
Name: livekit-plugins-uplift
Version: 0.2.9
Summary: Agent Framework plugin for voice synthesis with Uplift AI.
Project-URL: Homepage, https://github.com/V12Hero/livekit-plugins-uplift
Project-URL: Source, https://github.com/V12Hero/livekit-plugins-uplift
Project-URL: Tracker, https://github.com/V12Hero/livekit-plugins-uplift/issues
Author-email: V12Hero <support@v12hero.com>
License-Expression: Apache-2.0
License-File: LICENSE
Keywords: audio,livekit,realtime,tts,uplift,video,webrtc
Classifier: Intended Audience :: Developers
Classifier: License :: OSI Approved :: Apache Software License
Classifier: Programming Language :: Python :: 3
Classifier: Programming Language :: Python :: 3.9
Classifier: Programming Language :: Python :: 3.10
Classifier: Programming Language :: Python :: 3.11
Classifier: Programming Language :: Python :: 3.12
Classifier: Topic :: Multimedia :: Sound/Audio
Classifier: Topic :: Scientific/Engineering :: Artificial Intelligence
Requires-Python: >=3.9
Requires-Dist: aiohttp
Requires-Dist: livekit-agents[codecs]>=1.2.6
